tfc_toolbox_py/__init__.py
tfc_toolbox_py/account.py
tfc_toolbox_py/console.py
tfc_toolbox_py/converter.py
tfc_toolbox_py/cqupt.py
tfc_toolbox_py/file_operation.py
tfc_toolbox_py/math.py
tfc_toolbox_py/mysql_manager.py
tfc_toolbox_py/office_operation.py
tfc_toolbox_py/pip_manager.py
tfc_toolbox_py/spider.py
tfc_toolbox_py/sqlite_manager.py
tfc_toolbox_py/verilog.py
tfc_toolbox_py/webdav.py
tfc_toolbox_py-0.19.0.dist-info/METADATA
tfc_toolbox_py-0.19.0.dist-info/WHEEL
tfc_toolbox_py-0.19.0.dist-info/top_level.txt
tfc_toolbox_py-0.19.0.dist-info/RECORD
