Metadata-Version: 2.4
Name: tfc_toolbox_py
Version: 0.19.0
Summary: A tool box by TFC.
Author-email: TFC <1429316040@qq.com>
License-Expression: MIT
Project-URL: Homepage, https://gitee.com/iqdxa/tfc_toolbox_py
Project-URL: Issues, https://gitee.com/iqdxa/tfc_toolbox_py/issues
Classifier: Programming Language :: Python :: 3
Classifier: Operating System :: OS Independent
Classifier: Operating System :: POSIX :: Linux
Requires-Python: >=3.10
Requires-Dist: pandas
Requires-Dist: webdavclient3
Requires-Dist: mysql-connector-python
Requires-Dist: beautifulsoup4
